phis_doctor_advice/__init__.py
phis_doctor_advice/__main__.py
phis_doctor_advice-2025.7.23.3.dist-info/METADATA
phis_doctor_advice-2025.7.23.3.dist-info/WHEEL
phis_doctor_advice-2025.7.23.3.dist-info/licenses/LICENSE
phis_doctor_advice-2025.7.23.3.dist-info/RECORD
