Metadata-Version: 2.4
Name: phis-doctor-advice
Version: 2025.7.23.3
Summary: 慢病随访新建-医生建议
License-File: LICENSE
Requires-Python: >=3.12
